Topsis_102216038_srestha/__init__.py
Topsis_102216038_srestha/topsis.py
Topsis_102216038_srestha-0.3.dist-info/LICENSE.txt
Topsis_102216038_srestha-0.3.dist-info/METADATA
Topsis_102216038_srestha-0.3.dist-info/WHEEL
Topsis_102216038_srestha-0.3.dist-info/top_level.txt
Topsis_102216038_srestha-0.3.dist-info/RECORD
